odoo10_addon_project_closing-10.0.1.0.0.99.dev8-py2.7-nspkg.pth
odoo/addons/project_closing/README.rst
odoo/addons/project_closing/__init__.py
odoo/addons/project_closing/__manifest__.py
odoo/addons/project_closing/i18n/de.po
odoo/addons/project_closing/i18n/es.po
odoo/addons/project_closing/i18n/es_MX.po
odoo/addons/project_closing/i18n/fi.po
odoo/addons/project_closing/i18n/fr.po
odoo/addons/project_closing/i18n/hr.po
odoo/addons/project_closing/i18n/nl.po
odoo/addons/project_closing/i18n/nl_NL.po
odoo/addons/project_closing/i18n/project_closing.pot
odoo/addons/project_closing/i18n/pt.po
odoo/addons/project_closing/i18n/pt_BR.po
odoo/addons/project_closing/i18n/pt_PT.po
odoo/addons/project_closing/i18n/sl.po
odoo/addons/project_closing/i18n/tr.po
odoo/addons/project_closing/i18n/zh_CN.po
odoo/addons/project_closing/models/__init__.py
odoo/addons/project_closing/models/analytic.py
odoo/addons/project_closing/models/project.py
odoo/addons/project_closing/tests/__init__.py
odoo/addons/project_closing/tests/test_project.py
odoo10_addon_project_closing-10.0.1.0.0.99.dev8.dist-info/DESCRIPTION.rst
odoo10_addon_project_closing-10.0.1.0.0.99.dev8.dist-info/METADATA
odoo10_addon_project_closing-10.0.1.0.0.99.dev8.dist-info/RECORD
odoo10_addon_project_closing-10.0.1.0.0.99.dev8.dist-info/WHEEL
odoo10_addon_project_closing-10.0.1.0.0.99.dev8.dist-info/metadata.json
odoo10_addon_project_closing-10.0.1.0.0.99.dev8.dist-info/namespace_packages.txt
odoo10_addon_project_closing-10.0.1.0.0.99.dev8.dist-info/top_level.txt
